{"date":"2018-10-21T11:32:57.740Z","projects":[{"name":"Evergreen","stars":5442,"deltas":[117,203,486,1160,4,3,2],"monthly":[2861,3363,5325],"full_name":"segmentio/evergreen","description":"🌲 Evergreen React UI Framework by Segment","owner_id":819518,"pushed_at":"2018-10-20T14:25:00.000Z","tags":["react","component"],"contributor_count":34,"url":"https://evergreen.segment.com/","npm":"evergreen-ui","weekly":1975},{"name":"Omi","stars":3104,"deltas":[368,505,361,13,24,18,5],"monthly":[1668,1690,1718,2736],"full_name":"Tencent/omi","description":"Next generation web framework in 4kb JavaScript (Web Components + JSX + Proxy + Store + Path Updating)","owner_id":18461506,"pushed_at":"2018-10-20T14:39:57.000Z","tags":["framework"],"contributor_count":17,"url":"http://omijs.org","npm":"omi","weekly":1294},{"name":"30 seconds of code","stars":29440,"deltas":[71,110,152,151,248,319,92],"monthly":[16104,19683,21073,21385,21759,29369],"full_name":"30-seconds/30-seconds-of-code","description":"Curated collection of useful JavaScript snippets that you can understand in 30 seconds or less.","owner_id":43479428,"pushed_at":"2018-10-20T14:14:03.000Z","tags":["learning"],"contributor_count":143,"url":"https://30secondsofcode.org/","weekly":1143},{"name":"GraphQL.js","stars":1567,"deltas":[49,36,25,44,219,365,282],"monthly":[441,474,532,540,545,1518],"full_name":"f/graphql.js","description":"A Simple and Isomorphic GraphQL Client for JavaScript","owner_id":196477,"pushed_at":"2018-10-15T09:55:31.000Z","tags":["graphql"],"contributor_count":8,"npm":"graphql.js","weekly":1020},{"name":"VS Code","stars":62363,"deltas":[66,120,181,83,83,84,65],"monthly":[36031,42450,48275,55343,57493,59617,62297],"full_name":"Microsoft/vscode","description":"Visual Studio Code","owner_id":6154722,"pushed_at":"2018-10-20T20:26:50.000Z","tags":["ide"],"contributor_count":717,"url":"https://code.visualstudio.com","icon":"vscode.svg","weekly":682},{"name":"Percollate","stars":1731,"deltas":[68,93,70,162,248],"monthly":[1663],"full_name":"danburzo/percollate","description":"🌐 → 📖 A command-line tool to turn web pages into beautifully formatted PDFs","owner_id":205375,"pushed_at":"2018-10-18T08:37:28.000Z","tags":["scraping","pdf"],"contributor_count":6,"npm":"percollate","weekly":641},{"name":"Awesome","stars":94639,"deltas":[59,59,76,117,133,82,46],"monthly":[67573,76096,83285,89153,90953,92725,94580],"full_name":"sindresorhus/awesome","description":":sunglasses: Curated list of awesome lists","owner_id":170270,"pushed_at":"2018-10-20T16:58:01.000Z","tags":["meta"],"contributor_count":343,"icon":"awesome.svg","weekly":572},{"name":"Vue.js","stars":116872,"deltas":[50,94,98,106,81,80,46],"monthly":[70918,80649,91464,108007,111310,114334,116822],"full_name":"vuejs/vue","description":"🖖 A progressive, incrementally-adoptable JavaScript framework for building UI on the web.","owner_id":6128107,"pushed_at":"2018-10-20T09:49:30.000Z","tags":["framework","vdom","vue"],"contributor_count":194,"url":"http://vuejs.org","branch":"dev","npm":"vue","icon":"vue.svg","weekly":555},{"name":"React","stars":113530,"deltas":[54,89,67,81,98,60,46],"monthly":[78858,86175,93936,106742,109095,111548,113476],"full_name":"facebook/react","description":"A declarative, efficient, and flexible JavaScript library for building user interfaces.","owner_id":69631,"pushed_at":"2018-10-20T20:21:07.000Z","tags":["framework","vdom","react"],"contributor_count":1247,"url":"https://reactjs.org","npm":"react","icon":"react.svg","weekly":495},{"name":"Gridsome","stars":662,"deltas":[13,75,153,181,55],"monthly":[649],"full_name":"gridsome/gridsome","description":"⚡️  [WIP]  Build blazing fast websites with Vue.js & GraphQL","owner_id":17981963,"pushed_at":"2018-10-20T18:10:08.000Z","tags":["ssg","vue","graphql"],"contributor_count":3,"url":"https://gridsome.org","npm":"@gridsome/cli","weekly":477}]}
